microcosm_caching/__init__.py
microcosm_caching/base.py
microcosm_caching/build_info.py
microcosm_caching/decorators.py
microcosm_caching/factories.py
microcosm_caching/memcached.py
microcosm_caching-1.1.0.dist-info/LICENSE
microcosm_caching-1.1.0.dist-info/METADATA
microcosm_caching-1.1.0.dist-info/WHEEL
microcosm_caching-1.1.0.dist-info/entry_points.txt
microcosm_caching-1.1.0.dist-info/top_level.txt
microcosm_caching-1.1.0.dist-info/RECORD
